colourise/__init__.py
colourise-0.0.6.dist-info/LICENSE
colourise-0.0.6.dist-info/METADATA
colourise-0.0.6.dist-info/WHEEL
colourise-0.0.6.dist-info/top_level.txt
colourise-0.0.6.dist-info/RECORD
